{
    "appName": "Teams_Referral_Services",
    "version": "2.1.0",
    "isFromSample": true,
    "solutionSettings": {
        "name": "fx-solution-azure",
        "version": "1.0.0",
        "hostType": "Azure",
        "azureResources": [
            "function"
        ],
        "capabilities": [
            "Tab",
            "TabSSO"
        ],
        "activeResourcePlugins": [
            "fx-resource-frontend-hosting",
            "fx-resource-identity",
            "fx-resource-aad-app-for-teams",
            "fx-resource-function",
            "fx-resource-local-debug",
            "fx-resource-appstudio"
        ]
    },
    "programmingLanguage": "typescript",
    "defaultFunctionName": "getUserProfile",
    "projectId": "468f63f9-6118-4e40-83a3-9da5577bf36e"
}